odibi_de/__init__.py
odibi_de/azure_cloud_connector.py
odibi_de/core_types.py
odibi_de/pandas_engine.py
odibi_de/spark_engine.py
odibi_de/utils.py
odibi_de/version.py
odibi_de-0.2.3.dist-info/LICENSE
odibi_de-0.2.3.dist-info/METADATA
odibi_de-0.2.3.dist-info/WHEEL
odibi_de-0.2.3.dist-info/top_level.txt
odibi_de-0.2.3.dist-info/RECORD
