Metadata-Version: 2.1
Name: odibi-de
Version: 0.2.3
Summary: Personal data engineering framework using Pandas and Spark
Home-page: https://github.com/henryodibi11/odibi_de_project
Author: Henry Odibi
Author-email: henryodibi@outlook.com
Classifier: Programming Language :: Python :: 3
Classifier: Operating System :: OS Independent
Requires-Python: >=3.8
License-File: LICENSE
Requires-Dist: pandas
Requires-Dist: numpy
Requires-Dist: fastavro
Requires-Dist: fsspec
Requires-Dist: pyarrow
Requires-Dist: azure-storage-blob
Requires-Dist: pyspark
Requires-Dist: pyodbc
Requires-Dist: delta-spark
